lasfile/__init__.py
lasfile/known_sections.json
lasfile/lasfile.py
lasfile-0.2.4.dist-info/LICENSE
lasfile-0.2.4.dist-info/METADATA
lasfile-0.2.4.dist-info/WHEEL
lasfile-0.2.4.dist-info/entry_points.txt
lasfile-0.2.4.dist-info/top_level.txt
lasfile-0.2.4.dist-info/RECORD
