Metadata-Version: 2.2
Name: lasfile
Version: 0.2.4
Summary: A Python library for reading LAS files.
Project-URL: homepage, https://github.com/bzlmnop/lasfile
Keywords: las,CWLS,las logs,petrophysical logs
Requires-Python: >=3.7
License-File: LICENSE
Requires-Dist: numpy
Requires-Dist: pandas
Requires-Dist: apinum
